mycttestsdk/__init__.py
mycttestsdk/run.py
testmyct-1.0.0.dist-info/LICENSE
testmyct-1.0.0.dist-info/METADATA
testmyct-1.0.0.dist-info/WHEEL
testmyct-1.0.0.dist-info/top_level.txt
testmyct-1.0.0.dist-info/RECORD
