Metadata-Version: 2.1
Name: testmyct
Version: 1.0.0
Summary: Used for integration with Application monitoring systems
License-File: LICENSE
